pyfunctest/__init__.py
pyfunctest/docker.py
pyfunctest/fmod.py
pyfunctest/fmod_db.py
pyfunctest/fmods.py
pyfunctest/ftp.py
pyfunctest/git.py
pyfunctest/http.py
pyfunctest/httpserver.py
pyfunctest/kafka.py
pyfunctest/lfs.py
pyfunctest/migrate.py
pyfunctest/minio.py
pyfunctest/mysql.py
pyfunctest/postgre.py
pyfunctest/rabbitmq.py
pyfunctest-0.0.6.dist-info/LICENSE
pyfunctest-0.0.6.dist-info/METADATA
pyfunctest-0.0.6.dist-info/WHEEL
pyfunctest-0.0.6.dist-info/top_level.txt
pyfunctest-0.0.6.dist-info/RECORD
