Metadata-Version: 2.1
Name: pyfunctest
Version: 0.0.6
Summary: UNKNOWN
Home-page: https://github.com/Lunkov/pyfunctest
Author: Sergey Lunkov
License: MIT
Project-URL: Bug Tracker, https://github.com/Lunkov/pyfunctest/issues
Platform: UNKNOWN
Classifier: Programming Language :: Python :: 3
Classifier: License :: OSI Approved :: MIT License
Classifier: Operating System :: OS Independent
Requires-Python: >=3.6
License-File: LICENSE
Requires-Dist: gitpython
Requires-Dist: python-dotenv
Requires-Dist: docker
Requires-Dist: docker-compose
Requires-Dist: minio
Requires-Dist: mysqlclient
Requires-Dist: psycopg2
Requires-Dist: pika
Requires-Dist: kafka-python
